brightspace_api-2.1.0.dist-info/licenses/LICENSE
bsapi/__init__.py
bsapi/feedback.py
bsapi/helper.py
bsapi/oauth.py
bsapi/types.py
brightspace_api-2.1.0.dist-info/METADATA
brightspace_api-2.1.0.dist-info/WHEEL
brightspace_api-2.1.0.dist-info/top_level.txt
brightspace_api-2.1.0.dist-info/RECORD
