Metadata-Version: 2.4
Name: brightspace-api
Version: 2.1.0
Summary: Basic Python wrapper for the D2LValence Brightspace API using OAuth 2.0, with some added utilities and text to HTML conversion.
Author-email: Ciske Harsema <Ciske.Harsema@ru.nl>, Job Doesburg <Job.Doesburg@ru.nl>
License: MIT License
Requires-Python: >=3.10
License-File: LICENSE
Requires-Dist: requests
Dynamic: license-file
